{
  "locations": [
    { "id": "fertile-crescent", "name": "新月沃地", "nameEn": "Fertile Crescent", "type": "region", "parent": "middle-east" },
    { "id": "mesopotamia", "name": "美索不达米亚", "nameEn": "Mesopotamia", "type": "region", "parent": "middle-east" },
    { "id": "anatolia", "name": "安纳托利亚", "nameEn": "Anatolia", "type": "region", "parent": "turkey" },

    { "id": "yangtze-river", "name": "长江流域", "nameEn": "Yangtze River Valley", "type": "region", "parent": "china" },
    { "id": "yellow-river", "name": "黄河流域", "nameEn": "Yellow River Valley", "type": "region", "parent": "china" },
    { "id": "yunnan", "name": "云南", "nameEn": "Yunnan", "type": "region", "parent": "china" },
    { "id": "sichuan", "name": "四川", "nameEn": "Sichuan", "type": "region", "parent": "china" },
    { "id": "guangdong", "name": "广东", "nameEn": "Guangdong", "type": "region", "parent": "china" },
    { "id": "fujian", "name": "福建", "nameEn": "Fujian", "type": "region", "parent": "china" },
    { "id": "zhejiang", "name": "浙江", "nameEn": "Zhejiang", "type": "region", "parent": "china" },
    { "id": "jiangsu", "name": "江苏", "nameEn": "Jiangsu", "type": "region", "parent": "china" },
    { "id": "shandong", "name": "山东", "nameEn": "Shandong", "type": "region", "parent": "china" },
    { "id": "dongbei", "name": "东北", "nameEn": "Northeast China", "type": "region", "parent": "china" },
    { "id": "xinjiang", "name": "新疆", "nameEn": "Xinjiang", "type": "region", "parent": "china" },
    { "id": "inner-mongolia", "name": "内蒙古", "nameEn": "Inner Mongolia", "type": "region", "parent": "china" },
    { "id": "hubei", "name": "湖北", "nameEn": "Hubei", "type": "region", "parent": "china" },
    { "id": "hunan", "name": "湖南", "nameEn": "Hunan", "type": "region", "parent": "china" },

    { "id": "ganges", "name": "恒河流域", "nameEn": "Ganges Valley", "type": "region", "parent": "india" },
    { "id": "indus", "name": "印度河流域", "nameEn": "Indus Valley", "type": "region", "parent": "india" },
    { "id": "south-india", "name": "南印度", "nameEn": "South India", "type": "region", "parent": "india" },

    { "id": "southeast-asia", "name": "东南亚", "nameEn": "Southeast Asia", "type": "region", "parent": "asia" },
    { "id": "central-asia", "name": "中亚", "nameEn": "Central Asia", "type": "region", "parent": "asia" },
    { "id": "east-asia", "name": "东亚", "nameEn": "East Asia", "type": "region", "parent": "asia" },

    { "id": "mediterranean", "name": "地中海地区", "nameEn": "Mediterranean Region", "type": "region", "parent": "europe" },
    { "id": "iberian", "name": "伊比利亚半岛", "nameEn": "Iberian Peninsula", "type": "region", "parent": "europe" },

    { "id": "andes", "name": "安第斯山区", "nameEn": "Andes Mountains", "type": "region", "parent": "south-america" },
    { "id": "amazon", "name": "亚马逊流域", "nameEn": "Amazon Basin", "type": "region", "parent": "south-america" },

    { "id": "mesoamerica", "name": "中美洲", "nameEn": "Mesoamerica", "type": "region", "parent": "north-america" },
    { "id": "caribbean", "name": "加勒比地区", "nameEn": "Caribbean", "type": "region", "parent": "north-america" },

    { "id": "west-africa", "name": "西非", "nameEn": "West Africa", "type": "region", "parent": "africa" },
    { "id": "east-africa", "name": "东非", "nameEn": "East Africa", "type": "region", "parent": "africa" },
    { "id": "horn-of-africa", "name": "非洲之角", "nameEn": "Horn of Africa", "type": "region", "parent": "africa" },
    { "id": "nile-valley", "name": "尼罗河流域", "nameEn": "Nile Valley", "type": "region", "parent": "africa" }
  ]
}
